{"format_version":"1.12.0","minecraft:geometry":[{"description":{"identifier":"geometry.unknown","texture_width":128,"texture_height":256,"visible_bounds_width":13,"visible_bounds_height":10,"visible_bounds_offset":[0,1,0]},"bones":[{"name":"bone3","pivot":[0,16,0]},{"name":"bone2","parent":"bone3","pivot":[0,0,0]},{"name":"bone7","parent":"bone2","pivot":[0,0,0]},{"name":"bone6","parent":"bone7","pivot":[1,27,0],"cubes":[{"origin":[-7,26.5,-8],"size":[16,0,16],"uv":[-16,16]}]},{"name":"bone","parent":"bone2","pivot":[0,0,0]},{"name":"bone5","parent":"bone","pivot":[15,1,-15],"cubes":[{"origin":[-16,0.5,-16],"size":[32,32,32],"inflate":0.5,"uv":[0,64]}]},{"name":"bone4","parent":"bone","pivot":[0,13,0]},{"name":"bone8","parent":"bone4","pivot":[15,1,-15],"cubes":[{"origin":[-16,0.5,-16],"size":[32,32,32],"uv":[0,0]}]},{"name":"bone9","parent":"bone4","pivot":[15,1,-15],"cubes":[{"origin":[-16,0.5,-16],"size":[32,32,32],"uv":[0,128]}]},{"name":"bone10","parent":"bone4","pivot":[15,1,-15],"cubes":[{"origin":[-16,0.5,-16],"size":[32,32,32],"uv":[0,192]}]}]}]}